gomyck_mcp-1.0.0.dist-info/licenses/LICENSE
server/__init__.py
server/cdebug.py
server/demo.py
server/excel_read.py
server/mcp_sse.py
server/weather_query.py
gomyck_mcp-1.0.0.dist-info/METADATA
gomyck_mcp-1.0.0.dist-info/WHEEL
gomyck_mcp-1.0.0.dist-info/entry_points.txt
gomyck_mcp-1.0.0.dist-info/top_level.txt
gomyck_mcp-1.0.0.dist-info/RECORD
