Metadata-Version: 2.4
Name: gomyck-mcp
Version: 1.0.0
Summary: mcp server some code
Author-email: gomyck <hao474798383@163.com>
License-Expression: Apache-2.0
Requires-Python: >=3.10
License-File: LICENSE
Requires-Dist: gomyck-tools==1.3.3
Requires-Dist: httpx[socks]>=0.28.1
Requires-Dist: mcp[cli]>=1.6.0
Requires-Dist: openpyxl>=3.1.5
Requires-Dist: pandas>=2.2.3
Dynamic: license-file
